Metadata-Version: 1.0
Name: mb-distributions
Version: 0.4
Summary: Gaussian and Binomial distributions
Home-page: UNKNOWN
Author: Mani Bhushan
Author-email: manibhushan.cs@gmail.com
License: UNKNOWN
Platform: UNKNOWN
